factryengine/__init__.py
factryengine/models/__init__.py
factryengine/models/resource.py
factryengine/models/task.py
factryengine/scheduler/__init__.py
factryengine/scheduler/core.py
factryengine/scheduler/heuristic_solver/__init__.py
factryengine/scheduler/heuristic_solver/exceptions.py
factryengine/scheduler/heuristic_solver/main.py
factryengine/scheduler/heuristic_solver/matrix.py
factryengine/scheduler/heuristic_solver/task_allocator.py
factryengine/scheduler/heuristic_solver/window_manager.py
factryengine/scheduler/scheduler_result.py
factryengine/scheduler/task_batch_processor.py
factryengine/scheduler/task_graph.py
factryengine/scheduler/utils.py
factryengine-0.3.3.dist-info/LICENSE
factryengine-0.3.3.dist-info/METADATA
factryengine-0.3.3.dist-info/WHEEL
factryengine-0.3.3.dist-info/RECORD
