Metadata-Version: 2.1
Name: factryengine
Version: 0.3.3
Summary: production / job shop / resource scheduler for Python
License: MIT
Author: Jacob Østergaard Nielsen
Author-email: jacob.oestergaard.nielsen@gmail.com
Requires-Python: >=3.11,<4.0
Classifier: License :: OSI Approved :: MIT License
Classifier: Programming Language :: Python :: 3
Classifier: Programming Language :: Python :: 3.11
Classifier: Programming Language :: Python :: 3.12
Classifier: Programming Language :: Python :: 3.13
Requires-Dist: networkx (>=3.2.1,<4.0.0)
Requires-Dist: pandas (>=2.1.4,<3.0.0)
Requires-Dist: pydantic (>=2.5.3,<3.0.0)
Requires-Dist: seaborn (>=0.13.1,<0.14.0)
